semantic_router/__init__.py
semantic_router/linear.py
semantic_router/py.typed
semantic_router/route.py
semantic_router/schema.py
semantic_router/tokenizers.py
semantic_router/encoders/__init__.py
semantic_router/encoders/aurelio.py
semantic_router/encoders/azure_openai.py
semantic_router/encoders/base.py
semantic_router/encoders/bedrock.py
semantic_router/encoders/bm25.py
semantic_router/encoders/clip.py
semantic_router/encoders/cohere.py
semantic_router/encoders/encode_input_type.py
semantic_router/encoders/fastembed.py
semantic_router/encoders/google.py
semantic_router/encoders/huggingface.py
semantic_router/encoders/jina.py
semantic_router/encoders/litellm.py
semantic_router/encoders/local.py
semantic_router/encoders/mistral.py
semantic_router/encoders/nvidia_nim.py
semantic_router/encoders/ollama.py
semantic_router/encoders/openai.py
semantic_router/encoders/tfidf.py
semantic_router/encoders/vit.py
semantic_router/encoders/voyage.py
semantic_router/index/__init__.py
semantic_router/index/base.py
semantic_router/index/hybrid_local.py
semantic_router/index/local.py
semantic_router/index/pinecone.py
semantic_router/index/postgres.py
semantic_router/index/qdrant.py
semantic_router/llms/__init__.py
semantic_router/llms/base.py
semantic_router/llms/cohere.py
semantic_router/llms/llamacpp.py
semantic_router/llms/mistral.py
semantic_router/llms/ollama.py
semantic_router/llms/openai.py
semantic_router/llms/openrouter.py
semantic_router/llms/zure.py
semantic_router/llms/grammars/json.gbnf
semantic_router/routers/__init__.py
semantic_router/routers/base.py
semantic_router/routers/hybrid.py
semantic_router/routers/semantic.py
semantic_router/utils/__init__.py
semantic_router/utils/defaults.py
semantic_router/utils/function_call.py
semantic_router/utils/logger.py
semantic_router-0.1.11.dist-info/METADATA
semantic_router-0.1.11.dist-info/WHEEL
semantic_router-0.1.11.dist-info/licenses/LICENSE
semantic_router-0.1.11.dist-info/RECORD
