Metadata-Version: 2.4
Name: semantic-router
Version: 0.1.11
Summary: Super fast semantic router for AI decision making
Author-email: Aurelio AI <hello@aurelio.ai>
License-Expression: MIT
License-File: LICENSE
Requires-Python: <3.14,>=3.9
Requires-Dist: aiohttp<4,>=3.10.11
Requires-Dist: aurelio-sdk>=0.0.19
Requires-Dist: colorama<0.5,>=0.4.6
Requires-Dist: colorlog<7,>=6.8.0
Requires-Dist: litellm>=1.61.3
Requires-Dist: numpy>=1.25.2
Requires-Dist: openai<2.0.0,>=1.10.0
Requires-Dist: pydantic<3,>=2.10.2
Requires-Dist: pyyaml<7,>=6.0.1
Requires-Dist: regex>=2023.12.25
Requires-Dist: tiktoken<1.0.0,>=0.6.0
Requires-Dist: tornado<7,>=6.4.2
Requires-Dist: urllib3<3,>=1.26
Provides-Extra: all
Requires-Dist: boto3<2,>=1.34.98; extra == 'all'
Requires-Dist: botocore<2,>=1.34.110; extra == 'all'
Requires-Dist: cohere<6.00,>=5.9.4; extra == 'all'
Requires-Dist: dagger-io>=0.1.1; (python_version >= '3.11') and extra == 'all'
Requires-Dist: fastembed<0.4,>=0.3.0; (python_version < '3.13') and extra == 'all'
Requires-Dist: google-cloud-aiplatform<2,>=1.45.0; extra == 'all'
Requires-Dist: ipykernel<7,>=6.25.0; extra == 'all'
Requires-Dist: llama-cpp-python<0.2.86,>=0.2.28; (python_version < '3.13') and extra == 'all'
Requires-Dist: mistralai<0.1.0,>=0.0.12; extra == 'all'
Requires-Dist: mypy<2,>=1.7.1; extra == 'all'
Requires-Dist: ollama>=0.1.7; extra == 'all'
Requires-Dist: pillow<11.0.0,>=10.2.0; (python_version < '3.13') and extra == 'all'
Requires-Dist: pinecone<6.0.0,>=5.0.0; extra == 'all'
Requires-Dist: psycopg[binary]<4,>=3.1.0; extra == 'all'
Requires-Dist: pytest-asyncio<0.25,>=0.24.0; extra == 'all'
Requires-Dist: pytest-cov<5,>=4.1.0; extra == 'all'
Requires-Dist: pytest-mock<4,>=3.12.0; extra == 'all'
Requires-Dist: pytest-timeout; extra == 'all'
Requires-Dist: pytest-xdist<4,>=3.5.0; extra == 'all'
Requires-Dist: pytest~=8.2; extra == 'all'
Requires-Dist: qdrant-client<2,>=1.11.1; extra == 'all'
Requires-Dist: requests-mock<2,>=1.12.1; extra == 'all'
Requires-Dist: ruff<0.12,>=0.11.2; extra == 'all'
Requires-Dist: sentence-transformers>=5.0.0; (python_version < '3.13') and extra == 'all'
Requires-Dist: tokenizers>=0.19; (python_version < '3.13') and extra == 'all'
Requires-Dist: torch>=2.6.0; (python_version < '3.13') and extra == 'all'
Requires-Dist: torchvision>=0.17.0; (python_version < '3.13') and extra == 'all'
Requires-Dist: transformers>=4.36.2; (python_version < '3.13') and extra == 'all'
Requires-Dist: types-pyyaml<7,>=6.0.12.12; extra == 'all'
Requires-Dist: types-requests<3,>=2.31.0; extra == 'all'
Provides-Extra: bedrock
Requires-Dist: boto3<2,>=1.34.98; extra == 'bedrock'
Requires-Dist: botocore<2,>=1.34.110; extra == 'bedrock'
Provides-Extra: cohere
Requires-Dist: cohere<6.00,>=5.9.4; extra == 'cohere'
Provides-Extra: dev
Requires-Dist: dagger-io>=0.1.1; (python_version >= '3.11') and extra == 'dev'
Requires-Dist: ipykernel<7,>=6.25.0; extra == 'dev'
Requires-Dist: mypy<2,>=1.7.1; extra == 'dev'
Requires-Dist: pytest-asyncio<0.25,>=0.24.0; extra == 'dev'
Requires-Dist: pytest-cov<5,>=4.1.0; extra == 'dev'
Requires-Dist: pytest-mock<4,>=3.12.0; extra == 'dev'
Requires-Dist: pytest-timeout; extra == 'dev'
Requires-Dist: pytest-xdist<4,>=3.5.0; extra == 'dev'
Requires-Dist: pytest~=8.2; extra == 'dev'
Requires-Dist: requests-mock<2,>=1.12.1; extra == 'dev'
Requires-Dist: ruff<0.12,>=0.11.2; extra == 'dev'
Requires-Dist: types-pyyaml<7,>=6.0.12.12; extra == 'dev'
Requires-Dist: types-requests<3,>=2.31.0; extra == 'dev'
Provides-Extra: docs
Requires-Dist: pydoc-markdown>=4.8.2; (python_version < '3.12') and extra == 'docs'
Provides-Extra: fastembed
Requires-Dist: fastembed<0.4,>=0.3.0; (python_version < '3.13') and extra == 'fastembed'
Provides-Extra: google
Requires-Dist: google-cloud-aiplatform<2,>=1.45.0; extra == 'google'
Provides-Extra: local
Requires-Dist: llama-cpp-python<0.2.86,>=0.2.28; (python_version < '3.13') and extra == 'local'
Requires-Dist: sentence-transformers>=5.0.0; (python_version < '3.13') and extra == 'local'
Requires-Dist: tokenizers>=0.19; (python_version < '3.13') and extra == 'local'
Requires-Dist: torch>=2.6.0; (python_version < '3.13') and extra == 'local'
Requires-Dist: transformers>=4.36.2; (python_version < '3.13') and extra == 'local'
Provides-Extra: mistralai
Requires-Dist: mistralai<0.1.0,>=0.0.12; extra == 'mistralai'
Provides-Extra: ollama
Requires-Dist: ollama>=0.1.7; extra == 'ollama'
Provides-Extra: pinecone
Requires-Dist: pinecone<6.0.0,>=5.0.0; extra == 'pinecone'
Provides-Extra: postgres
Requires-Dist: psycopg[binary]<4,>=3.1.0; extra == 'postgres'
Provides-Extra: qdrant
Requires-Dist: qdrant-client<2,>=1.11.1; extra == 'qdrant'
Provides-Extra: vision
Requires-Dist: pillow<11.0.0,>=10.2.0; (python_version < '3.13') and extra == 'vision'
Requires-Dist: torch>=2.6.0; (python_version < '3.13') and extra == 'vision'
Requires-Dist: torchvision>=0.17.0; (python_version < '3.13') and extra == 'vision'
Requires-Dist: transformers>=4.36.2; (python_version < '3.13') and extra == 'vision'
